<repas nom="En hommage à Antoine Parmentier..." offset="8" type="déjeuner">
<plat nom="MAIS SUREMI" type="entrée">
<ingrédient nom="SUREMI">
<quantité unit="gr">
<age-6>40</age-6>
<age6-12>50</age6-12>
<age12>50</age12>
</quantité>
</ingrédient>
<ingrédient nom="MAIS">
<quantité unit="gr">
<age-6>40</age-6>
<age6-12>50</age6-12>
<age12>50</age12>
</quantité>
</ingrédient>
</plat>
<plat nom="HACHIS PARMENTIER" type="plat">
<ingrédient nom="HACHIS PARMENTIER">
<quantité unit="gr">
<age-6>200</age-6>
<age6-12>250</age6-12>
<age12>300</age12>
</quantité>
</ingrédient>
</plat>
<plat nom="FROMAGE BLANC" type="dessert">
<ingrédient nom="FROMAGE BLANC">
<quantité unit="pièce">
<age-6>1</age-6>
<age6-12>1</age6-12>
<age12>1</age12>
</quantité>
</ingrédient>
</plat>
<plat nom="COOKIES">
<ingrédient nom="COOKIES">
<quantité unit="pièce">
<age-6>2</age-6>
<age6-12>2</age6-12>
<age12>2</age12>
</quantité>
</ingrédient>
</plat>
</repas>